[
    {
        "key": "datr",
        "value": "V_yeaSkgtGl60p1BWUl9gg89",
        "domain": "facebook.com",
        "path": "/",
        "hostOnly": false,
        "creation": "2026-02-28T11:39:22.506Z",
        "lastAccessed": "2026-02-28T11:39:22.507Z"
    },
    {
        "key": "sb",
        "value": "V_yeaUAj7J11qh_yiFlPNQEp",
        "domain": "facebook.com",
        "path": "/",
        "hostOnly": false,
        "creation": "2026-02-28T11:39:22.507Z",
        "lastAccessed": "2026-02-28T11:39:22.507Z"
    },
    {
        "key": "locale",
        "value": "en_US",
        "domain": "facebook.com",
        "path": "/",
        "hostOnly": false,
        "creation": "2026-02-28T11:39:22.507Z",
        "lastAccessed": "2026-02-28T11:39:22.507Z"
    },
    {
        "key": "vpd",
        "value": "v1%3B672x360x2",
        "domain": "facebook.com",
        "path": "/",
        "hostOnly": false,
        "creation": "2026-02-28T11:39:22.507Z",
        "lastAccessed": "2026-02-28T11:39:22.507Z"
    },
    {
        "key": "c_user",
        "value": "61587169087435",
        "domain": "facebook.com",
        "path": "/",
        "hostOnly": false,
        "creation": "2026-02-28T11:39:22.507Z",
        "lastAccessed": "2026-02-28T11:39:22.507Z"
    },
    {
        "key": "xs",
        "value": "44%3A6fIJdlFHMNAN4Q%3A2%3A1772186623%3A-1%3A-1",
        "domain": "facebook.com",
        "path": "/",
        "hostOnly": false,
        "creation": "2026-02-28T11:39:22.507Z",
        "lastAccessed": "2026-02-28T11:39:22.507Z"
    },
    {
        "key": "pas",
        "value": "61587487970647%3AerRxODI9VJ%2C61587616012999%3AS6IFh6o95B%2C61587169087435%3AsCGaDeabti",
        "domain": "facebook.com",
        "path": "/",
        "hostOnly": false,
        "creation": "2026-02-28T11:39:22.507Z",
        "lastAccessed": "2026-02-28T11:39:22.507Z"
    },
    {
        "key": "ps_l",
        "value": "1",
        "domain": "facebook.com",
        "path": "/",
        "hostOnly": false,
        "creation": "2026-02-28T11:39:22.507Z",
        "lastAccessed": "2026-02-28T11:39:22.507Z"
    },
    {
        "key": "ps_n",
        "value": "1",
        "domain": "facebook.com",
        "path": "/",
        "hostOnly": false,
        "creation": "2026-02-28T11:39:22.507Z",
        "lastAccessed": "2026-02-28T11:39:22.507Z"
    },
    {
        "key": "fr",
        "value": "0yJPA6KxtLZSdc5Qe.AWcKlNWiA2mKMt3QaAAP0V31dAeojgQDsEtEusSroGUgWSaScLs.BpnvxX..AAA.0.0.BpotDg.AWdaDiaNeQ_no_Rd4JfkNEB2OG4",
        "domain": "facebook.com",
        "path": "/",
        "hostOnly": false,
        "creation": "2026-02-28T11:39:22.507Z",
        "lastAccessed": "2026-02-28T11:39:22.507Z"
    },
    {
        "key": "fbl_st",
        "value": "100421738%3BT%3A29537966",
        "domain": "facebook.com",
        "path": "/",
        "hostOnly": false,
        "creation": "2026-02-28T11:39:22.507Z",
        "lastAccessed": "2026-02-28T11:39:22.507Z"
    },
    {
        "key": "wl_cbv",
        "value": "v2%3Bclient_version%3A3100%3Btimestamp%3A1772277984",
        "domain": "facebook.com",
        "path": "/",
        "hostOnly": false,
        "creation": "2026-02-28T11:39:22.507Z",
        "lastAccessed": "2026-02-28T11:39:22.507Z"
    }
]
